jarvis_sdk/NLU.py
jarvis_sdk/Skill.py
jarvis_sdk/__init__.py
open_jarvis_sdk-0.0.1.dist-info/LICENSE
open_jarvis_sdk-0.0.1.dist-info/METADATA
open_jarvis_sdk-0.0.1.dist-info/WHEEL
open_jarvis_sdk-0.0.1.dist-info/top_level.txt
open_jarvis_sdk-0.0.1.dist-info/RECORD
