Metadata-Version: 2.1
Name: open-jarvis-sdk
Version: 0.0.1
Summary: Software Development Kit for varius AI tasks including Intent Parsing & more
Home-page: https://github.com/open-jarvis/sdk
Author: Philipp Scheer
Author-email: hi@fipsi.at
License: UNKNOWN
Platform: UNKNOWN
Classifier: Programming Language :: Python :: 3
Classifier: License :: OSI Approved :: MIT License
Classifier: Operating System :: POSIX :: Linux
Classifier: Operating System :: MacOS
Requires-Python: >=3.6
